{"慢性胃炎,RF,干燥综合症": 763, "腰痛原因待查": 550, "乳腺增生泌尿道感染": 764, "肾结石": 249, "肝炎后肝硬变": 765, "糖耐量异常": 316, "急性胃炎": 192, "原发性肝胆管细胞癌多发转移腹水": 1496, "轻度不典型增生": 766, "吞咽困难原因待查": 317, "冠心病": 4, "食道多发乳头状瘤": 767, "口腔": 768, "返流性食道炎": 182, "慢性浅表萎缩性胃炎": 406, "三叉神经病": 274, "糖尿病": 18, "颈椎病": 49, "脑膜外出血": 770, "慢性浅表性胃炎,反流性食管炎": 552, "腹泻原因待查": 223, "瘀热证": 246, "肠炎？": 553, "肠化生": 772, "慢性胃炎,胃食管反流病?": 551, "十二批肠球炎": 774, "肝硬化失代偿期": 122, "黄疸？冠心病": 775, "胰腺钙化": 776, "HT,CHD": 554, "胃炎,反流性食道炎": 777, "腹胀等查": 778, "慢性胃炎伴肠化": 44, "泄泻": 83, "丙型肝炎": 779, "左肾错构瘤": 780, "贲门胃切除术后": 781, "吻合口炎": 782, "腹胀肝脾不调": 783, "大便次数增多": 555, "上咀嚼道感染": 784, "慢性胃炎,十二指肠球炎": 437, "胆管结石？": 785, "幽门螺杆菌相关性胃炎": 32, "慢性浅表性胃炎,颈椎病": 438, "脂肪肝原发性高血压": 1373, "牙痛": 786, "酒精性肝硬化": 787, "口苦,胃胀痛": 788, "过敏性皮炎": 790, "皮肌炎": 439, "周围神经病变": 265, "晕厥原因待查气虚证": 556, "泄泻胃肠功能失调": 791, "子宫脱垂": 792, "CAG中度下降": 557, "贲门癌术后1年余": 793, "甲状腺机能减退": 318, "肩关节疼痛": 1435, "腹胀": 24, "恶心,头痛": 794, "咳嗽原因待查": 796, "兼阳虚": 797, "胸痛原因待查": 798, "早搏": 799, "慢性胰腺炎?": 355, "糖尿病周围神经痛": 800, "腹胀,泌尿系感染,白内障": 801, "急性扁桃体炎": 802, "直肠炎脾虚泄泻": 356, "脱发": 183, "血小板减低": 225, "肥胖": 319, "咽炎过敏性鼻炎": 803, "支气管火": 440, "高粘血症": 804, "抑郁证": 805, "CAG,腹泻,脂肪肝": 806, "肠粘连,高血压病": 807, "脂肪肝泌尿系感染": 441, "幽门螺旋杆菌感染?": 808, "萎缩性胃炎伴胆汁反流": 177, "面部色斑": 810, "咽痛,口苦": 558, "腹胀肠不全梗阻": 811, "肠上皮化生轻度": 559, "胃角溃疡": 812, "（行动不便）": 76, "腹痛肠虚寒": 813, "心功能不全": 275, "甲低,特发性水肿": 833, "皮肤骚痒": 560, "牙齦出血": 561, "口腔异味脾胃积热": 562, "头晕": 442, "冠心病,胆结石": 735, "胃痛脾胃虚弱": 563, "贲门癌": 817, "乳腺结节（性质待定）": 443, "子宫内膜癌术后": 564, "伴轻度颈腺增生及肠化生": 818, "结肠息肉": 60, "CHD": 819, "胆囊炎,胆结石": 565, "腹泻,便血": 820, "泌尿道感染": 88, "HP+,肠鸣,痛经": 821, "类风湿": 822, "胆囊炎": 14, "恶心待查": 566, "2型糖尿病": 25, "慢性肾功能衰竭尿毒症期维持血透": 1439, "腹部不适": 823, "肾错构瘤": 276, "全身异味原因待查": 824, "慢性浅表性胃炎": 17, "肾囊肿": 93, "慢性肝炎": 567, "酒精性肝炎": 825, "视网膜出血": 568, "视网膜动脉硬化": 357, "慢性浅表性胃窦炎": 826, "泌尿系感染高血压": 827, "肺炎冠心病": 358, "大肠息肉": 828, "肠化": 161, "月经失调": 155, "肾移植术后,感冒": 829, "反复口腔溃疡": 830, "胆囊多发息肉": 156, "头晕待查": 266, "肾功能衰竭": 831, "重度肠化胆汁反流性胃炎": 832, "失眠,口苦": 569, "胃癌术后": 444, "右上腹疼痛待查": 834, "窦性心动过缓": 320, "肠粘连高脂血症": 174, "泌尿系感染": 53, "恶心寒湿中阻": 835, "胆囊多发结石": 97, "十二指肠球部多发溃疡": 279, "肥胖病": 837, "头发早白": 1228, "皮肤痒": 445, "十二指肠癃起": 570, "胆囊结合": 839, "心悸待查": 152, "十二指肠球部多发息肉": 840, "食道鳞状上皮增生": 250, "胆管炎": 571, "肝多发囊肿": 359, "下半身畏寒原因待查": 841, "不完全性肠梗阻2年": 842, "上腹痛原因待查": 360, "脾肾阳虚证": 843, "慢性萎缩性胃炎重试肠上皮化生": 844, "特发性房颤": 505, "浅表性胃炎肠化中度": 226, "呕吐原因待查": 277, "咳嗽": 193, "白细胞减少": 361, "肝部分术后24年": 846, "脂肪肝胆囊结石": 847, "胆汁反流性胃炎": 61, "泄泻肝气乘脾证": 848, "萎缩性胃炎伴不典型增生": 849, "贲门息肉": 572, "高血压": 13, "焦虑状态": 773, "非特异性结肠炎": 850, "肝纤维化,糖尿病": 851, "慢性支气管火": 852, "复发性胰腺炎": 853, "失眠阴虚火旺": 573, "肝脾不调）": 854, "舌道憩室": 855, "HP+?": 574, "腹痛湿热内蕴": 856, "脐周不适,气虚感冒": 575, "淋巴结肿大": 227, "反流性食物炎": 857, "HP++": 576, "（痞满": 1054, "呕血？": 859, "胃肠多发息肉": 446, "Hp+?": 860, "下肢发麻原因待查": 861, "胃脘不适,右肾缩少": 862, "湿热中阻": 863, "黑便待查": 864, "慢性胃炎甲减": 865, "慢性胃炎HP+？": 866, "泌感": 362, "慢性肾小球肾炎": 228, "慢性胃炎,痞满": 867, "心脾两虚证": 868, "心悸": 80, "焦虑症": 1057, "舌炎": 116, "CA199增高原因待查": 869, "腹泻,胃痛": 870, "反复上呼吸道感染": 577, "功能性胃炎": 871, "腹痛原因待": 872, "萎缩性胃炎伴肠化": 181, "月经后期": 579, "慢性腹泻（行动不便）": 873, "紫癜": 447, "盆腔炎": 162, "腹水": 229, "DM,高血脂症,结肠切除术": 874, "皮肤黄原因待查": 580, "肠消化不良": 875, "水肿待查": 876, "CSG,结肠息肉管状腺瘤2级": 877, "上腹胀满疼痛": 878, "体重下降": 635, "维生素C缺乏(抗坏血酸缺乏)": 448, "心悸心律失常": 771, "腺上皮高度异型增生吻合口狭窄": 880, "乏力,纳差": 881, "天疱疮": 882, "高脂血症反流性食管炎": 883, "眩晕气血不足证": 884, "眩晕（行动不便）": 885, "慢性胃炎伴糜烂": 96, "子宫内膜术后": 582, "胸椎压缩性骨折": 886, "胃肠功能失常": 363, "泄泻脾虚兼夹湿热": 887, "慢性腹泻(脾虚证)": 583, "神经功能症": 888, "失眠": 11, "腹痛待查胆囊炎": 889, "唇炎": 251, "慢性萎缩性胃炎伴腺体增生肠化": 890, "心动过缓": 891, "Hp(+)": 892, "慢性腹泻脾虚湿热内蕴": 893, "慢性胃炎先天性溶血性黄疸": 894, "DM": 252, "慢性阑尾炎?": 895, "小肠炎": 896, "胃胀,胃痛": 584, "肾阳虚": 897, "十二指肠糜烂性炎": 898, "胃息肉Hp+": 899, "反流性管炎": 900, "冠心病关节疼痛": 364, "皮肤瘙痒": 365, "食道炎冠心病": 901, "足痛待查": 902, "恶心": 204, "十二指肠溃疡食道裂孔疝": 449, "慢性非特异性溃疡性结肠炎": 585, "肝胃郁热证": 586, "消化道出血": 903, "Hp（＋＋＋）": 904, "慢性萎缩性胃炎广泛肠上皮化生": 905, "脂肪肝,胆囊结石": 906, "郁证（行动不便）": 907, "失眠症高血压病": 450, "右上腹疼痛原因待查": 587, "浅表性胃炎伴胆汁反流": 908, "慢性萎缩性胃炎重度肠化": 909, "慢性胃炎心律失常": 468, "小肠梗阻": 910, "慢性胃炎腺上皮增生": 911, "心悸,高血压病": 912, "慢性胃炎（行动不便）": 163, "功能性消化不良？": 913, "克罗恩病": 588, "慢性阻塞性肺病": 589, "肾病综合症": 914, "HP+": 71, "慢性胃炎,甲状腺结节": 915, "肝结石": 916, "睡眠障碍": 12, "高血压痌": 1357, "上腹痛待查": 321, "功能性消化功能": 917, "慢性胃炎十二指肠溃疡": 918, "阴虚火旺证": 919, "泄泻湿热内蕴": 920, "口苦": 81, "肺Ca": 836, "结肠癌": 322, "肠炎？输尿管结石？": 921, "偏头痛": 590, "慢性胆囊炎,慢性胃炎,脂肪肝": 922, "胃痛,慢性胃炎": 923, "肝部分切除术后": 591, "胆囊切除术后发热待查": 924, "肝癌切除术后": 925, "皮肤干燥": 926, "失眠,气虚感冒": 592, "左肾囊肿湿热内蕴": 927, "外阴湿疹": 928, "体重下降原因待查": 451, "感冒": 89, "干眼症": 280, "异型增生": 366, "CSG,HP++": 929, "脾虚泄泻肺癌术后": 323, "胃下重": 930, "难治性溃疡": 931, "心悸窦性心动过速": 932, "胆结石": 29, "口干待查": 175, "类癌": 933, "高胆红素血症,非新生儿": 281, "胃炎,胆囊炎": 879, "子宫切除术后": 934, "胃息肉": 50, "月经不调": 140, "腔隙性脑梗塞": 594, "重度骨质疏松": 324, "肝硬变": 936, "反流性食管炎,慢性胃炎": 452, "溃疡性结肠炎?": 937, "肾囊肿(后天性)": 253, "HT": 367, "口唇干裂": 938, "阑尾切除术后": 963, "胃痛,感冒": 939, "肠易激综合症": 194, "胃脘不适,胃寒": 940, "高脂血症＋": 941, "胃痛,胃胀,眠中介齿": 942, "小肠嗜酸性粒细胞浸润高血压病": 943, "湿热内阻": 944, "便秘慢性胃炎": 935, "脂代谢异常": 531, "脂肪肝慢性胃炎": 946, "胆结石,冠心病,感冒": 947, "兼痰热": 595, "食管平滑肌瘤": 948, "咽部溃疡": 949, "嗳气不畅": 950, "气血不足": 596, "胸痛": 368, "药物性肝损伤": 597, "性性胃炎": 1016, "肝囊炎": 952, "胃炎冠心病": 953, "胆管癌术后": 954, "肝脓肿": 325, "二尖瓣三尖瓣反流（轻度）": 955, "胆囊癌术后": 956, "关节疼痛": 56, "眼睑浮肿原因待查": 957, "口腔溃疡": 30, "脂肪肝（行动不便）": 453, "大便不成形": 176, "腮腺炎": 1220, "肠套叠": 958, "胃胀,腹胀,HT": 1198, "慢性胃炎肝胃不调": 959, "高血压便秘": 598, "口腔溃疡十二指肠球部溃疡": 599, "慢性胃炎慢性胃炎心律失常": 960, "浅表萎缩性胃炎": 961, "失眠,乏力": 962, "胆囊炎湿热内蕴,肝肾阴虚": 370, "肝癌术后": 593, "肝脏弥漫病变": 964, "关节疼痛感冒": 965, "黑便原因待查": 966, "肝硬化,肝结石": 967, "慢性胃炎,反流性食道炎,DM,胆囊炎": 1093, "胆红素增高": 969, "反流食管炎": 454, "虚体感冒": 600, "肺气肿伴感染": 970, "慢性胃炎肠化": 195, "痹证": 601, "湿疹": 90, "骨质疏松症": 971, "咽痛": 972, "浮肿待查": 141, "肺内结节原因待定": 724, "肢体疼痛": 973, "尿失禁": 602, "口腔溃疡,面部痤疮": 974, "失代偿期低蛋白血症腹水脾大": 975, "脾大原因待查": 976, "结肠多发息肉": 326, "慢性萎缩性胃炎伴轻度不典型增生": 977, "十二指肠息肉": 231, "Hp＋＋": 978, "神经性头痛": 603, "舌痛": 1164, "急性胰腺炎？": 979, "功能性消失不良": 205, "骨转移": 455, "兼肾虚": 232, "口苦待查": 233, "脾略大原因待查": 980, "便血原因待查痔疮？": 981, "结肠炎?": 371, "消化性溃疡？慢性胃炎": 982, "消瘦待查": 327, "胆囊结石": 36, "腹胀,肝功异常": 983, "冠心病高血压糖尿病": 984, "胃溃疡？十二指肠溃疡？": 985, "面色萎黄": 605, "精神抑郁症": 986, "腹胀,失眠": 987, "颈椎病？": 988, "皮炎脑动脉硬化": 989, "前列腺增大": 215, "食管憩室": 606, "十二指肠球部溃疡？": 372, "慢性萎缩性胃炎,反流性食道炎": 456, "慢性萎缩性胃炎伴中度肠化": 206, "贲门失弛缓症？": 991, "虚劳脾肾阳虚（行动不便）": 992, "上焦热盛,脾胃虚寒": 457, "面神经麻痹": 607, "糖尿病肾病冠心病": 1250, "Hp+高血压病": 458, "慢性浅表性胃炎轻度肠上皮化生": 994, "腹胀肠粘连": 995, "抑郁症": 207, "便秘": 6, "尿道炎": 459, "脾大腹腔积液": 1456, "耳聋": 282, "食管炎": 75, "慢性胃炎,糖尿病": 996, "功能性消化不良肝脾胃不调": 997, "胰腺肿瘤": 998, "结肠癌术后": 208, "泄泻肝郁脾虚": 1076, "视网膜动脉硬化脑动脉硬化前列腺增生": 1000, "脂肪肝,腹痛,腹胀": 1001, "发现腹水近三个": 1002, "慢性肠炎": 283, "食道之": 1003, "脑供血不足": 373, "慢性胃炎,胃溃疡,高血压": 1004, "十二指肠溃疡？": 374, "腹中灼热感原因待查": 608, "白细胞减少症": 284, "右侧股动脉斑块形成": 460, "慢性十二指肠溃疡Hp＋": 609, "脾虚泄泻": 66, "胃胀": 42, "高血压病心律失常房颤": 610, "纳差": 131, "胃肠功能紊乱": 34, "慢性胃炎,食道炎": 1005, "胃溃疡并出血": 1006, "肝内结节原因待查": 1007, "伴轻度颈腺丧生及肠化生": 1008, "胰头癌": 815, "腰椎间盘突出": 209, "右上腹痛原因待查": 254, "泌尿感感染": 1009, "慢性胃炎慢性阑尾炎？": 611, "CSG伴胆汁返流": 1010, "心脏神经官能症": 612, "慢性阑尾炎": 375, "腰痛": 101, "IBS": 676, "眩晕": 255, "萎缩性胃炎伴轻度肠化": 614, "barrett食管": 615, "右肾囊肿": 522, "肝硬化": 94, "慢性胃炎,胃食管反流病": 616, "尿道结石?": 473, "胆囊息肉,脂肪肝": 1013, "胁痛胆管结石?胆管炎": 1014, "腰痛上感冠心病": 234, "萎缩性胃炎中度肠化食道炎": 1015, "左肾多发囊肿": 951, "前列腺增生": 41, "腹胀,嗳气": 1388, "TB增设原因待查": 1017, "胃下垂?": 1018, "腹胀4天": 1019, "慢性浅表性疣状胃炎": 1020, "胃肠功能失调": 19, "双侧大脑中动脉狭窄": 1021, "肠道菌群失调症": 1022, "眼干燥综合征": 349, "右下腹痛": 1023, "便秘原因待查": 1024, "DM,支扩": 1025, "直肠癌切除术后": 377, "胃肠功能失调hp+": 1026, "功能性消化不良失眠症": 1027, "功能性消化不诮": 1028, "十二指肠球后溃疡": 1029, "月经量多": 1030, "舌面裂纹": 617, "脾肾不足兼湿热": 1031, "胃炎": 78, "乏力原因待查": 256, "肝功异常,先天性非溶血性黄疸": 235, "胃溃疡?": 184, "腹胀原因待查": 257, "皮肤过敏": 1032, "小肠吸收不良综合征(非手术性)": 286, "混合痔?": 1511, "Barrett食管？": 287, "功能性消失不良,腹泻": 378, "脾胃虚寒": 379, "腰痛待查": 236, "双乳腺增生": 462, "发热待查": 463, "腹泻耳鸣": 1034, "慢性胃炎伴胆汁反流": 99, "胃痛脾胃虚寒": 512, "胃溃疡": 46, "食道溃疡": 258, "皮肢瘙痒": 618, "胃部分切除术后": 619, "心脏神经官能症,鼻炎": 1036, "脾虚泄泻慢性胃炎": 1037, "大便粘,纳差,湿疹": 1038, "高脂血症,腹胀": 1039, "十二脂肠溃疡": 464, "强柱": 465, "麦粒肿,便秘": 1040, "高脂血症脑梗": 1041, "大脑动脉瘤": 620, "肺癌术后": 153, "脚气": 1042, "胆内胆管结石": 1043, "贫血脾大": 621, "腹痛腹泻待查": 1044, "牙龈出血": 259, "舌苔厚": 1045, "舌根僵硬": 809, "脂肪肝,高血压病,慢性胃炎,食道炎": 1046, "功能性消化不衣": 622, "类风湿关节炎": 288, "药物性肝损害?": 1047, "颈淋巴结肿大": 1048, "心悸心脾两虚证": 1049, "腹部畏寒,糖尿病": 1050, "腰椎尖盘突出症（行动不便）": 1051, "不典型增生": 466, "乙肝病毒携带者": 1052, "反流性食道炎？": 380, "食管Ca?": 1053, "胰腺癌": 623, "纳差,胃胀": 624, "结肠冗长": 858, "泄泻寒热昏杂": 1055, "HP感染": 328, "腰肌劳损": 1056, "叶酸缺乏": 278, "无不适": 1058, "口腔异味痛经": 1059, "肝脓肿术后": 1060, "慢性胃炎（行动不动）": 467, "舌痛,DM,HT,骨关节病": 1061, "子宫附件切除术后": 340, "萎缩性胃炎（中度）": 1062, "右肾结石": 626, "阑尾炎术后,腹胀,胆囊炎": 627, "胃食管反流病": 98, "结肠息肉术后": 628, "DU": 123, "肝囊肿,2型糖尿病": 629, "腹胀待查": 54, "干燥综合征": 289, "痰饮内停": 1063, "肾功能不全": 630, "腹泻": 33, "Du": 1064, "慢性荨麻疹": 1065, "PTCA术后": 381, "胸憋原因待查": 631, "嗳气肝胃不和": 632, "胃胀,右胁胀": 1066, "心律失常房颤": 382, "全身畏寒": 469, "胃胀肝脾不调": 1067, "肝囊肿": 23, "结肠憩室": 633, "胃底多发息肉": 1068, "淋巴瘤术后": 1069, "口腔异味,慢性咽炎": 1070, "高血压病？": 1071, "慢性胃炎脾胃虚弱": 470, "膀胱癌术后": 471, "慢性胃炎,胆囊息肉": 634, "肝功能异常原则待查": 1072, "胃肠功能失调症": 636, "发现CEA增高原因待查": 1073, "骨质疏松慢性胃炎": 472, "高尿酸血症": 84, "慢性萎缩性胃炎肠化": 117, "泄泻脾肾两虚证": 1074, "冠心病心梗PTCA术后": 637, "附件囊肿": 638, "结肠炎？": 1075, "血尿待查": 639, "慢性腹泻高压病病": 999, "感冒风热证": 1077, "慢性萎缩性胃炎伴糜烂": 383, "足部真菌感染": 1078, "二度房室传导阻滞": 1079, "膝关节痛": 1012, "高血压病上腹痛待查": 1080, "功能性消化不良脾胃虚弱": 196, "肺癌切除术后": 1081, "化疗胃肠道反应": 640, "总胆管结石": 1082, "出血性胃炎": 1083, "HP+++": 474, "原发性小肠吸收不良综合征": 1084, "肛门湿疹": 1085, "高血压病,肾Ca,恶心": 1086, "高脂血症高尿酸血症": 1087, "慢性胃炎,十二指肠球炎,脂肪肝": 1088, "肠道菌群失常": 384, "口干阴虚证（行动不便）": 385, "脑动脉硬化": 133, "蟃性胃炎": 642, "头痛": 157, "急性十二指肠溃疡": 1089, "胁痛": 51, "乙状结肠炎": 643, "急性胰腺炎": 386, "涎多原因待查": 1090, "脂肪肝,胆囊多发息肉": 1091, "食管癌术后": 1092, "黄疸": 968, "耳鸣待查": 1211, "便血": 237, "慢性腹泻脾胃虚弱": 1095, "脂肪肝,脂代谢异常": 1096, "残胃癌": 1097, "慢性胃炎,DU": 1098, "胃肠功能失调,失眠": 1099, "呕吐待查": 158, "血小板减少": 387, "支气管炎上呼吸道感染": 1100, "高血压病,腹痛待查": 644, "头痛待查": 329, "慢性浅表性胃炎伴胆汁返流": 475, "外伤": 645, "舌麻,眠中咬舌": 1101, "十二指肠溃疡高脂血症": 1102, "眩晕心悸气血不足证": 1103, "银屑病": 1104, "慢性萎缩性胃炎": 7, "肠道菌群失调": 35, "肝火内盛": 1105, "上腹痛待查消化性溃疡?": 1106, "大便异常": 238, "青光眼": 646, "阑尾炎术后,腹胀": 1107, "痔疮": 85, "支气管哮喘心衰": 1108, "肝占位性病变?": 1181, "肺部小结节": 1110, "甲状腺炎": 1111, "萎缩性胃炎肠化": 159, "右侧腹痛": 1112, "增生": 290, "毛囊炎": 111, "痹症": 1113, "脂肪肝,肝功能异常": 647, "甲状腺功能减退症": 1114, "急性阑尾炎": 1115, "颈部疼痛": 1116, "头部疖肿": 476, "冠心病冠心病": 1117, "幽门螺旋杆菌感染": 77, "Hp+": 112, "梅核气": 655, "腹痛肝气乘脾": 477, "慢性胃吻合口炎": 497, "泌尿系感染结膜炎": 648, "慢性胃炎乳腺增生": 649, "上呼吸道感染食道炎": 1118, "肝转移癌": 1119, "胃多发息肉（行动不便）": 650, "右侧胸腔积液": 1244, "胃肠炎": 1120, "乳腺癌术后": 239, "脑血拴慢性胃炎": 478, "发热等查": 652, "幽门螺杆菌感染": 461, "急性胃炎?": 1121, "慢性胃炎伴不轻度不典型增生": 430, "阴虚证": 388, "泪囊炎": 1122, "子宫内膜异味症": 990, "脚气病": 1282, "反流性食道炎头痛": 389, "更年期综合症": 479, "胃平滑肌瘤": 331, "呕吐痰热中阻": 1124, "barret食管": 178, "神经衰弱": 1125, "目干": 480, "胁痛待查": 210, "腰椎骨关节病": 1126, "硒缺乏": 1127, "十二脂肠憩室": 1128, "房颤": 261, "胆总管部分梗阻": 1129, "双下肢动脉硬化": 1130, "胃切除史": 1131, "口干阴虚证": 653, "胆囊炎湿热内蕴": 654, "干燥综合征？": 1327, "双下肢无力待查": 1328, "(行动不便）": 262, "毛细血管扩张症": 1132, "HP＋": 27, "反流性食道炎": 9, "泌尿系感染急性胃肠炎": 1134, "慢性胃炎HP＋": 1481, "高血压病": 3, "泄泻脾胃虚寒": 656, "咽炎腰椎尖盘突出症（行动不便）": 391, "慢性胃炎,咽炎": 1135, "萎缩性胃炎": 55, "舌木,口咸": 1136, "兼郁热": 1137, "轻度肠化": 481, "急性肠炎": 392, "胃痛,胃食管反流病": 1138, "HP+？": 1139, "慢阻肺伴感染": 482, "脾肾两虚": 1140, "呃逆": 211, "贲门炎": 1141, "脂肪肝肝脾不调": 1142, "上热下寒": 1143, "急性胰腺炎?": 1144, "支气管哮喘并感染": 1145, "反流性食道炎（行动不便）": 291, "体虚感冒": 292, "恶心,纳差,肝功异常": 1146, "附件炎": 263, "月经量少": 483, "右肾错构瘤": 657, "胃炎胃溃疡": 1147, "慢性轻中度萎缩性胃炎伴中度肠化": 179, "乙状结肠癌术后": 1148, "食道平滑肌瘤": 147, "大便异常原因待查": 484, "失眠障碍": 1149, "腹痛肝气痗脾": 658, "便秘肝脾不调": 393, "尿耐量异常": 1150, "下肢血管闭塞症术后": 541, "颈椎病上呼吸道感染": 1152, "肝内结石": 660, "小便泡沫原因待查": 1153, "浅表性胃炎肠化中度耳鸣": 1154, "胃痛气阴两虚": 1155, "颈椎病?": 1156, "膀胱炎": 1157, "功能性消化不良": 2, "胃肠功能失调肝脾不调": 394, "慢性胃炎胆囊炎": 1158, "泄泻脾胃虚弱证": 1159, "高血压病慢性胃炎心律失常": 332, "黄斑变性": 395, "乳腺增生": 57, "四肢凉": 485, "甲亢": 333, "舌面裂纹,感冒": 1160, "慢性胃炎伴腺体增生": 212, "脂溢性皮炎": 662, "慢性支气管炎十二指肠溃疡": 486, "腹部胃寒": 1161, "冠心病心悸": 1162, "盗汗": 487, "荨麻疹": 197, "烧心,口干苦": 1163, "郁证痰气郁结": 604, "湿浊阻滞中焦": 1165, "2型糖尿病双下肢动脉硬化": 488, "白癜风": 1166, "贲门失弛缓症": 396, "留置导尿": 789, "慢性萎缩性胃炎中度肠化": 663, "不完全性肠梗阻": 92, "虹膜睫状体炎": 664, "慢性胃炎脑梗": 1167, "肝功异常?": 1168, "大使不规律": 1169, "自身免疫性肝炎,类风湿关节炎": 1170, "反流性食管炎?": 1171, "痞满,纳差": 1172, "（行动不便）冠心病": 1173, "痛风": 293, "脂肪肝,胆囊息肉,高尿酸血症,高脂血症": 247, "结肠息肉高血压病心律失常": 1174, "肺部感染": 665, "消化性溃疡?": 185, "贫血": 198, "胃间质瘤": 166, "功能性消化不良,反复感冒,尿血待查": 814, "慢性胆囊炎": 113, "直肠类癌术后": 489, "脑梗塞": 124, "排气多": 1176, "反复呼吸道感染": 148, "肠粘连": 82, "腹泻,胃脘畏寒,咳痰,牙痛": 1177, "先天性食管裂孔疝": 248, "支气管扩张": 666, "不完全性肠梗阻?": 1178, "糖代谢异常": 1179, "伴肠化颈椎病": 1180, "痰多": 1109, "颈腺增生轻度": 1182, "神经性胃炎": 1183, "反流性食道炎Barrett食管": 267, "泄泻脾胃虚弱": 268, "维生素缺乏": 667, "头晕原因待查": 1184, "食道ca前列腺增生症": 668, "胁胀": 490, "幽门螺杆菌相关性胃炎?": 669, "慢性结肠炎": 74, "慢性胃炎轻度不典型增生": 269, "上感脑梗": 491, "肺纤维化": 1185, "口干,口苦,烧心,手心热,心悸": 1186, "胃窦占位": 107, "骨髓增生性贫血": 1361, "双下肢静脉曲": 1188, "乳腺增生,慢性胃炎": 1189, "肾实质性高血压病": 1190, "食道炎2型糖尿病": 492, "植物神经功能紊乱": 1191, "恶心,呕吐": 1192, "消化性溃疡": 79, "脑震荡后遗症": 1193, "食流性食管炎": 397, "慢性胃炎伴轻度不典型增生": 398, "肝右叶小结节原因待查": 1194, "食道ca骨质疏松": 1195, "酒精性肝病": 670, "胃痛,腹泻": 1196, "便溏": 1197, "肾盂肾炎": 399, "兼湿热": 369, "肾结石？": 671, "功能性消化不良,心悸": 1199, "慢性胃炎,hp+": 1200, "腹胀失眠": 672, "高指血症": 334, "心悸口干口苦": 1201, "胆囊多发息肉,慢性胃炎": 1202, "一直服用阿司匹林": 1203, "口腔异味": 47, "脘痞": 673, "先天性溶血性黄疸": 674, "胆囊炎？": 167, "肝郁脾虚": 1204, "郁证": 294, "耳鸣胃火上炎": 1205, "吞咽困难原因待查食道炎?": 675, "慢性胃炎小肠病变不除外": 1206, "HP＋＋＋": 613, "CAG": 118, "尿路感染": 493, "食道裂孔疝": 335, "急性咽炎": 1363, "腹痛原因待查": 125, "UBT：HP＋": 1207, "胃下垂": 87, "腹部肿瘤？": 1208, "食道炎": 16, "脾胃虚弱": 213, "慢性萎缩性胃炎？": 295, "胃溃疡？": 214, "慢性胃炎（行动不便）胃溃疡？盆腔炎": 677, "膝骨关节病": 1209, "胰腺囊肿": 494, "牙龈炎": 336, "反流性食管炎": 10, "肝内钙化灶": 1210, "胆囊切除术后（行动不便）": 495, "前列腺增生慢性肾炎": 1094, "口腔异味胃热证": 678, "腹泻,气虚感冒": 1212, "慢性肾炎": 270, "腹膜炎": 1213, "慢性胃炎伴不典型增生肠化": 496, "强直性脊柱炎": 337, "腹痛肠道湿热": 1214, "双下肢肿": 679, "反流性食道炎耳鸣": 338, "单纯性膈肌痉挛": 680, "口腔乏力": 1215, "体重减轻(待查)": 661, "萎缩性胃炎不典型增生": 216, "脂肪肝,DU,慢性胃炎,干眼症": 681, "上腹胀满": 1216, "黄褐斑": 682, "痰气交阻": 1217, "大便不调": 1218, "脾虚湿热证": 683, "大细胞性贫血": 1219, "肝功能异常": 67, "缺铁性贫血": 164, "鼻咽炎": 1221, "子宫内膜异位": 684, "便秘高血压病": 240, "慢性胃炎,消化性溃疡?": 1222, "胃痛": 28, "腹中包块原因待查": 1223, "直肠炎": 134, "口腔溃疡伴感染": 1224, "轻度脂肪肝": 142, "肺气肿": 330, "身体下降原因待查": 1225, "四肌无力原因待查": 1226, "变应性荨麻疹": 1227, "消瘦": 339, "嗳气": 135, "肾小球肾炎": 498, "HP（+）": 1229, "反流性反流性高血压病": 499, "22型糖尿病": 1230, "肝内胆管结石": 149, "慢性胃炎中度肠化": 1231, "耳鸣": 108, "慢性胃炎,食管炎": 1232, "小肠溃疡": 685, "肝功异常": 102, "舌胀": 1233, "大便中有粘液": 1234, "HP+,咽炎": 1235, "CSG,食管炎,失眠,便秘,心悸": 1236, "浅表性胃炎结肠癌术后": 1237, "甲状腺肿大": 400, "肝郁化火": 1033, "胆管结石": 217, "CSG（明日开始服奥美拉唑）": 1239, "胆管Ca术后": 1240, "恶心原因待查": 1241, "慢性乙型肝炎": 218, "慢性胃炎": 1, "胸闷": 126, "过敏性紫癜": 500, "功能性消化不良,反复感冒": 1242, "肝功能异常?": 1243, "心律失常气虚感冒高脂血症": 651, "丙型病毒性肝炎": 686, "骨质疏松": 45, "慢性十二指肠溃疡": 1245, "慢性胃炎反酸,胸闷,嗳气": 1246, "Hp＋": 73, "HP+,呃逆": 1247, "慢性胃炎,功能性消化不良肝胃不和": 1248, "病毒性结膜炎": 687, "糖尿病肾病": 1350, "盆腔积液原因待查": 1249, "慢性萎缩性胃炎中度颈腺增生及肠上皮化生": 219, "泌尿道感染?": 401, "上呼吸道感染": 22, "食道炎Hp＋": 993, "聚证(气滞湿阻)": 1251, "功能性消化不良寒热错杂": 1502, "食道Ca放化疗后": 1252, "上热下寒证": 689, "直肠腺瘤术后": 690, "脂肪肝,胆结石": 1253, "慢性浅表性胃炎伴胆汁反流": 1254, "慢性浅表性胃炎,食道炎": 1255, "胆囊息肉": 20, "呕吐待查冠心病": 691, "2糖尿病": 1256, "上感": 127, "慢性咽炎": 58, "抑郁状态": 1257, "骨髓纤维化": 308, "泄泻肝气乘脾": 1259, "HP+,慢性胃炎,腹胀": 1260, "上腹痛等查慢性胃炎胃溃疡": 1261, "舌炎脾胃虚弱": 1262, "贲门息肉2型糖尿病": 692, "背痛待查": 501, "脂肪瘤": 502, "胰腺癌术后": 1263, "慢性胃炎病理示细胞增生活跃": 1264, "脂肪肝\\前列腺增生": 1265, "脂肪肝（重度）": 1266, "胆囊炎腹水": 1238, "左肾切除术后": 136, "急性阑尾炎?": 1267, "视物模糊": 260, "直肠息肉": 199, "食道炎高血压病": 693, "湿热泄泻": 694, "胆结石,冠心病": 403, "肝脾不调": 503, "结肠息肉高血压病": 1268, "食道癌": 143, "十二指肠球部溃疡": 63, "帕金森综合症": 695, "肠梗阻": 1269, "冠心病PCI术后": 696, "RF,肝功异常,发热待查": 1270, "晕厥原因待查": 504, "泄泻脾胃湿热证": 697, "泄泻脾肾阳虚兼湿热": 845, "贲门下隆起慢性胃炎": 1271, "不成形": 1272, "吻合口溃疡": 1273, "病毒性上呼吸道感染": 404, "十二指肠溃疡": 106, "腹痛肝脾不调": 1274, "镜下血尿待查": 1275, "急性上呼吸道感染": 1276, "咯血待查": 1375, "结肠炎": 21, "DU,胃炎伴糜烂": 1278, "腹部不适,失眠": 698, "重度脂肪肝": 1279, "慢性胃炎,胃胀": 1280, "短暂性脑缺血": 405, "小肠虚寒": 1281, "高血砡病": 1123, "关节疼痛冠心病": 1283, "过敏性鼻炎(变应性鼻炎)": 128, "腹胀,反酸,腹泻,便血": 1284, "前列腺增生症": 160, "乏力待查气血不足": 296, "双肺结节": 1285, "卵巢囊肿": 506, "脾大": 109, "慢性胃炎心悸": 769, "转氨酶升高": 1286, "过敏性鼻炎": 168, "脂肪肝,DM,高脂血症": 1287, "腹泻,腹痛,感冒": 1288, "Hp感染": 1289, "胆源性胰腺炎": 1290, "胃NHL化疗后慢性萎缩性胃炎": 1291, "甲状腺切除术后": 699, "膀胱癌": 1292, "痞满脾胃虚弱": 407, "慢性胃炎,2型糖尿病,高血压病": 1293, "肩周炎": 1294, "心肌炎": 1295, "宫颈癌术后": 1296, "兼湿热内蕴": 1297, "口腔异味胃肠功能失调": 1298, "肝血管瘤？": 1299, "失眠前列腺肥大": 1300, "直肠癌": 408, "胆汁返流性胃炎": 700, "胆总管空肠吻合术后": 1301, "肠息肉": 1302, "慢性胃炎伴轻度肠化": 103, "肠鸣": 507, "胸闷待查": 110, "痤疮带下": 701, "高尿酸症": 702, "内伤发热": 703, "失眠高血压病": 409, "慢性胃炎伴胆汁返流": 704, "直肠切除术后": 705, "胃溃疡？盆腔炎": 1303, "脂肪肝,高血压病": 1304, "功能异常原因待查": 1305, "高脂血症": 5, "（行动不便）关节疼痛": 1306, "脾虚湿热": 1307, "纳呆": 297, "烧心": 298, "肝硬化腹水": 1308, "乳腺癌": 299, "脂肪肝结肠息肉电切术后": 1309, "脑梗帕金森氏病": 1310, "高血压病1级": 508, "麦粒肿": 1311, "酒精性肝硬化失代偿期腹水尿血原因待查胆囊结石": 1312, "血脂血症": 706, "便秘（寒热错杂": 1313, "高脂血症肝脾胃不调": 509, "萎缩性胃炎伴肠上皮化生": 1314, "十二指肠癃起物性质待定": 1315, "腹泻待查": 410, "腹泻（脾肾虚寒）": 1316, "口疮溃疡": 707, "伴肠化": 708, "胸膜肥厚(胸膜纤维化)": 1317, "脘胀": 709, "心功能不全慢性胃炎": 710, "食管癌切除术后": 411, "慢性胃炎,过敏性皮炎": 1318, "间质慢性炎": 1319, "萎缩性胃炎腺体肠化轻－中度不典型增生": 138, "溃疡性结肠炎": 220, "口苦,失眠": 1321, "咽下困难(待查)": 412, "高脂血症（行动不便）": 1322, "甲状腺癌术后": 1323, "脑血栓": 1324, "慢性胃炎；胸膜炎": 1325, "肝区不适原因待查": 510, "功能性消化性不良": 1326, "慢性萎缩性胃炎,食道炎": 390, "肝癌": 511, "中医": 241, "自汗": 711, "气管炎": 300, "消化不良": 40, "慢笥胃炎": 1329, "慢性胃炎胸痛待查": 712, "B超发现肝脏异常": 1330, "咽炎,胃炎": 1331, "冠心病?": 713, "腹泻型": 714, "癫痫": 341, "胆管息肉": 1035, "口腔异味失眠": 1332, "结膜炎": 68, "胃窦占位食道炎": 1333, "贫血待查": 1334, "骨骼纤维化": 715, "甲亢？": 1335, "腰椎间盘突出症": 271, "乏力待查": 716, "面部痤疮": 43, "萎缩性胃炎肠化＋": 1336, "甲状腺囊肿": 1337, "胆囊炎,胃食管反流病": 1338, "反流性食道炎糖尿病": 1339, "胃胀慢性胃炎": 1340, "胃道Ca": 1341, "胆管癌": 717, "胆结石慢性胃炎": 200, "结肠多发憩室": 513, "脾胃虚弱）": 1342, "食道炎？": 718, "CSG,DU": 413, "寒热错杂症": 1343, "咳嗽,口腔异味": 1344, "尿少原因待查": 1345, "脑出血后遗症": 1346, "左上腹不适": 1347, "汗多原因待查": 719, "上消化道出血消化性溃疡": 1519, "慢性胃炎,腹痛": 720, "子宫内膜Ca": 1348, "吞咽困难": 1349, "手足心热": 688, "乳腺癌切除术后": 1351, "骨关节炎": 1352, "胰腺炎": 414, "肾转移": 514, "肠化中度": 415, "结缔组织病原发性胆汁性肝硬化": 1353, "肝血管瘤": 105, "腹泻,胆囊切除术后": 1354, "多囊卵巢综合征(斯-利二氏综合征)": 1355, "痞满肝胃郁热": 1356, "短睡眠者": 416, "慢性胃炎伴糜烂出血上皮增生": 376, "子宫内膜肌腺癌放化疗术后": 1358, "胃溃疡（行动不便）": 721, "扁桃体炎": 1359, "慢性胃炎脾胃虚寒证": 417, "肾癌术后": 1360, "慢性肾功能衰竭尿毒症期": 342, "肠化高血压病": 343, "慢性胃炎,食管炎,肝功异常": 1187, "反流病食道炎": 1362, "腹痛脾胃虚寒": 1133, "呕吐原因待查慢性胃炎": 1364, "病理：肠化异型增生": 1365, "混合痔": 191, "肺癌": 132, "胃痉挛？": 722, "慢性浅表性胃炎,上呼吸道感染": 544, "脾虚虚弱": 1367, "舌苔黄": 1368, "慢性胃肠炎": 1369, "CAG中度": 418, "慢性胃炎伴增生肠化": 516, "子宫肌瘤": 114, "便秘,感冒": 1370, "肾虚腰痛": 419, "陈旧性肺结核": 1371, "皮肤痛痒": 1372, "慢性胰腺炎": 169, "颈动脉动脉硬化": 795, "胆囊腺肌症": 517, "甲减": 170, "鼻炎": 201, "Barrett食管": 273, "胆囊肿": 1374, "过敏性哮喘": 1277, "慢性喘息性支气管炎": 1376, "慢性萎缩性胃炎伴肠化": 52, "亚临床甲状腺功能减退症": 723, "胆红素高原因待查": 1377, "口苦肺胃热盛证": 1378, "带状疱疹": 1379, "血管性头痛": 1380, "肠道感染": 1381, "女性慢性盆腔炎": 301, "气虚感冒": 64, "淋巴瘤": 1382, "湿热内蕴": 144, "肠吸收不良": 1383, "贲门下粘膜隆起间质细胞瘤？": 1384, "皮肤感染": 302, "汗多": 1385, "腹痛?": 1386, "胃间质瘤腹痛待查": 1387, "胃窦占位食道炎脑梗": 345, "反流性食道炎脂肪肝": 129, "大便次数多": 303, "颈动脉硬化": 285, "急性胃肠炎": 304, "冠心病PTCA术后": 346, "胃痉挛": 1389, "月量经多": 1390, "肝内强回声性质待定": 1391, "小肠吸收不良综合症": 1392, "腹胀上热下寒证": 725, "胁痛肝气郁结": 1393, "腹泻,胁痛": 1394, "骨关节病": 186, "风湿性心脏病": 420, "慢性胃炎,心律失常": 726, "神经性皮炎": 518, "十二指肠球炎": 69, "失眠胆结石": 1395, "骨血管瘤": 1396, "肺部感染?": 1397, "眩晕舌炎": 1398, "慢性胃从": 1399, "多发胆囊息肉": 421, "骨囊肿": 1400, "泄泻,便秘,贫血": 1401, "门脉高压": 519, "腹胀,腹痛": 305, "脾脾胃不和": 1402, "胸骨后堵闷感,便秘": 1403, "慢性腹泻": 15, "更年期综合征": 306, "肠梗阻?": 1404, "上呼吸道感染Hp＋": 727, "食管裂孔功能障碍": 1405, "慢性胃炎伴糜烂轻度肠化": 1406, "肝功能异常肝脾不调": 307, "中度脂肪肝": 180, "痞满,胃痛": 1407, "外痔": 242, "咽部有痰": 1258, "高血压冠心病": 1409, "腹胀湿浊中阻": 1410, "盗汗原因待查": 728, "冠心病心律失常": 729, "盆腔积液": 1411, "大便不畅": 520, "便秘带下": 730, "脑梗": 72, "下肢麻木": 1412, "消化性溃疡2型糖尿病": 1413, "呼吸不畅待查": 521, "脂肪肝,胆囊炎": 1414, "萎缩性胃炎伴重度肠化": 1415, "十二指肠憩室炎": 1416, "寒热错杂": 1011, "慢性胃炎伴胆汁反流心悸": 731, "食管下段隆起": 1417, "贲门癌术后": 309, "颈动脉硬化伴斑块形成": 272, "肠炎": 171, "双肾结石": 187, "慢性萎缩性胃炎（行动不便）": 732, "低热": 1418, "前列腺炎": 119, "胁部不适": 1419, "纳差肝脾胃不调": 1420, "口臭,肝功能异常,脂肪肝": 1421, "胃肠型感冒": 1422, "牙周炎": 310, "少腹不适,稍感腹胀,腹痛": 1423, "胃癌": 1424, "便秘待查": 1425, "功血": 1426, "胸痛待查": 311, "反流炎": 1427, "血管神经性头痛": 1428, "慢性浅表性胃炎伴肠化": 422, "腹痛待查": 26, "腹泻,腹痛": 1429, "接触性皮炎": 1430, "胃大部切除术后": 1431, "卵巢癌术后": 423, "脘腹胀满": 1432, "肾癌": 1433, "肝胃郁热": 733, "脾虚胃热": 523, "支气管炎": 39, "CSG": 130, "腹痛": 31, "慢性鼻炎": 578, "腹泻脾胃虚弱hp+": 1434, "消化性溃疡？": 224, "肠化HP＋": 347, "直肠癌术后": 348, "腹痛待查泌尿系感染,肠炎": 524, "肠梗阻术后": 525, "眼痛待查": 734, "十二指肠憩室": 1436, "心律失常室性早搏": 816, "伴肠化中度": 1437, "前列腺増生": 1438, "糜烂性胃炎": 150, "痞满": 65, "慢性肾功能不全": 312, "食管下段平滑肌瘤": 1440, "口甜待查": 1441, "胃食道反流病": 736, "多汗待查": 526, "皮炎": 145, "DU?": 1442, "口干,纳差": 1443, "失眠,纳差": 1444, "喉炎": 1445, "子宫肌腺症": 1408, "血小板减少症": 313, "手足凉": 737, "肝区疼痛原因待查": 1446, "慢性胃炎食管裂孔疝": 527, "高血压病食道炎": 1447, "消瘦原因待查": 528, "呕吐": 529, "白塞氏病": 221, "慢性胆囊炎肝胃不调": 1448, "肾虚证": 1449, "腹痛脾虚虚寒": 1542, "脑血栓形成": 1450, "胆结石,功能性消化不良,2型糖尿病,感冒": 1451, "兼有郁热": 530, "甲状腺结节": 95, "上呼吸道感": 1452, "左踝软组织损伤": 1453, "肠易激综合征": 62, "肝功异常原因待查": 243, "肝ca": 1454, "肝功能不全": 945, "目干目涩": 738, "食管炎,慢性胃炎,胆囊炎": 1455, "舌炎,乳腺增生": 532, "右胁不适": 424, "慢性萎缩性胃炎肠上皮化生": 230, "食管溃疡": 533, "胃食管食": 1457, "乏力待查脾肾两虚": 739, "胰腺结节": 740, "下腹痛待查": 741, "心梗": 425, "纳差,消瘦": 1458, "失眠症": 38, "肠功能紊乱": 188, "腹痛肝气乘脾肠道菌群失调": 1459, "功能性消化不良心脾两虚证": 1460, "慢性支气管炎": 172, "动脉硬化": 426, "食道CA？前列腺增生": 350, "血细胞减少": 1461, "HTDM脂肪肝": 1462, "腹中不适": 742, "脂肪肝": 8, "脂肪肝,胆结石,慢性胃炎": 1463, "高血压病胆囊息肉": 1464, "阑尾周围炎": 581, "前列腺炎?": 427, "慢性胃炎,咳嗽": 1466, "右上腹痛待查": 534, "高胆固醇血症": 1467, "皮肤干裂": 1468, "胃粘膜脱垂": 1469, "舌干": 743, "CRF": 1470, "体检": 744, "慢性浅表性胃炎伴糜烂": 428, "胆囊胆固醇沉着症": 351, "乏力,胃痛": 1471, "干燥综合症": 745, "浅表性胃炎": 59, "咽干": 535, "慢性胃炎？": 1472, "咽炎": 48, "脐左上方不适": 1473, "口臭": 91, "腹部不适脾胃虚寒": 1474, "高血病史": 746, "继发性血小板减少症": 1475, "慢性胃炎伴糜烂肠化": 202, "结肠黑便质高脂血症": 1175, "多囊卵巢综合征": 536, "原发性高血压": 537, "失眠症（重度）": 429, "腹部不适原因待查": 1476, "痞满,HP+": 747, "痛经": 244, "冠心病？": 352, "纳差,体重下降,感冒": 1477, "痞满肝脾不调": 1478, "小便混浊高血压病": 1479, "前列腺肥大": 538, "急性胆囊炎？": 641, "变应性哮喘": 1480, "腹泻脾胃虚弱": 1549, "甲状腺功能减退": 539, "结肠黑变病": 165, "腹痛待查慢性阑尾炎？": 1482, "乳腺增生症": 748, "慢性胃炎,心悸": 1483, "脑血拴": 540, "慢性食管炎": 1151, "肺ca": 1484, "慢性胃炎关节疼痛": 1485, "阴道炎": 189, "直肠溃疡": 1486, "咯血等查": 1487, "泄泻脾虚虚弱": 1488, "上腹痛原因待查慢性胃炎?胃囊炎?": 1489, "萎缩性胃炎伴颈腺增生及肠上皮化生": 749, "食管裂孔疝": 86, "早孕": 1490, "夜间磨牙原因待查": 1491, "关节痛": 137, "乏力": 190, "胁痛肝功异常": 750, "汗证": 154, "腹腔积液原因待查结核性腹膜炎？": 1492, "感冒冠心病": 1493, "上焦有热": 1494, "发热原因待查": 751, "HP+,HT,CHD,DM": 542, "关节病": 1495, "慢性胃炎伴中度肠化": 173, "口干苦": 752, "脾大原因待因": 659, "食道静脉瘤": 431, "药物性肝损害": 753, "胃脘不适": 151, "腹痛待查慢性胃炎急性胰腺炎？": 1497, "便秘,头痛": 1498, "急性胆囊炎？高尿酸血症": 1499, "功能性消化不良,关节疼痛": 1500, "便血待查": 838, "便秘失眠肾虚": 1501, "慢性畏炎": 402, "口腔导味,头面部皮肤疖肿": 1503, "结肠黑便病": 1504, "慢重下降": 1505, "面部疖肿": 1506, "高血压?": 1507, "肝气郁结": 432, "克隆恩病": 1508, "泄泻（脾胃虚寒）": 1509, "胃多发息肉": 120, "糖尿病病": 1510, "反流性食道炎,慢性胃炎": 754, "右上腹痛": 543, "肝占位": 1512, "溶血性黄疸": 1320, "胆囊炎,胆结石,脂肪肝": 755, "上呼吸道感冒": 1513, "溃疡性结肠炎？": 756, "口臭湿热内蕴": 1514, "发热待查上呼吸道感染": 757, "原发性血小板增高症": 1515, "头痛,慢性胃炎": 1516, "高血压病HP＋": 1517, "中呼吸道感染": 1518, "口臭待查": 104, "肾虚": 1520, "腹痛待查肠炎阑尾周围炎": 1465, "慢性阻塞性肺疾病": 1521, "慢性胃炎,反流性食管炎": 314, "肝部分切除后": 758, "腰椎增生": 139, "过敏性小肠炎": 1522, "行动不便": 1366, "腹痛等查": 515, "角膜炎": 1523, "反食性食道炎": 1524, "反流性食道炎（行動不便）": 1525, "上腹痛": 344, "肺Ca术后": 759, "脂肪肝肾结石": 1526, "左肾囊肿": 1527, "高脂血症失眠": 353, "胃息肉？": 1528, "心律失调": 1529, "脑动脉硬化前列腺增生": 436, "萎缩性咽炎": 760, "白内障": 546, "胆囊炎?": 547, "萎缩性胃炎肠化＋＋＋": 1530, "陈旧性心梗": 433, "口苦口臭": 434, "冠心病病": 761, "CEA增高原因待查": 548, "嗳气,咽痒,咳嗽": 1531, "结肠息肉病": 1532, "心律失常": 37, "腹痛待查冠心病": 1533, "小肠息肉": 315, "慢性胆囊炎,慢性胃炎,": 1534, "高血压高血压": 1535, "胃切除术后": 1536, "颈动脉狭窄": 435, "维生素缺乏症": 1537, "阴道出血": 1538, "结肠下垂": 1539, "直肠炎脾虚泄泻（行动不便）": 1540, "吞咽困难原因待查食道癌": 1541, "口干": 70, "白塞病": 354, "关节炎": 203, "高血压病同": 1543, "易感冒": 222, "咯血原因待查": 1544, "风湿性关节炎": 1545, "腰痛高尿酸血症冠心病": 1546, "急性胰腺炎反流性食道炎": 1547, "骨髓增生异常综合征": 1548, "支气管哮喘": 100, "残胃炎": 264, "浮肿原因待查": 1550, "复合维生素Ｂ缺乏": 1557, "胆汁反流": 1551, "胆囊切除术后": 121, "CA199升高原因待查": 1552, "感冒肝肾阴虚": 762, "颈部不适待查": 625, "大便不规律": 146, "痞满,咳嗽": 1553, "慢性胃炎脾胃虚弱证": 1554, "反酸": 545, "气虚证": 1555, "胆石症": 115, "小脑萎缩": 1556, "胃食管返流病": 549, "hp+": 245, "反流性食道炎冠心病": 1558}